fastrates/__init__.py
fastrates/__main__.py
fastrates/main.py
fastrates-0.1.0.dist-info/entry_points.txt
fastrates-0.1.0.dist-info/WHEEL
fastrates-0.1.0.dist-info/METADATA
fastrates-0.1.0.dist-info/RECORD
