Metadata-Version: 2.1
Name: fastrates
Version: 0.1.0
Summary: 
Author: yagizd
Author-email: yagizcanilbey1903@gmail.com
Requires-Python: >=3.8,<4.0
Classifier: Programming Language :: Python :: 3
Classifier: Programming Language :: Python :: 3.8
Requires-Dist: requests (>=2.24.0,<3.0.0)
Requires-Dist: typer[all] (>=0.3.1,<0.4.0)
